README.md
setup.py
lazy_async/__init__.py
lazy_async.egg-info/PKG-INFO
lazy_async.egg-info/SOURCES.txt
lazy_async.egg-info/dependency_links.txt
lazy_async.egg-info/not-zip-safe
lazy_async.egg-info/top_level.txt