Metadata-Version: 2.1
Name: lazy-async
Version: 0.7
Summary: Lazy evaluation for function/method/property getter
Home-page: https://github.com/jqqqqqqqqqq/
Author: Curtis Jiang
License: MIT
Keywords: Lazy Evaluation,Decorator
Platform: UNKNOWN
Classifier: Development Status :: 4 - Beta
Classifier: License :: OSI Approved :: MIT License
Classifier: Intended Audience :: Developers
Classifier: Intended Audience :: End Users/Desktop
Classifier: Programming Language :: Python :: 3 :: Only
Classifier: Programming Language :: Python :: 3.7
Classifier: Topic :: Software Development :: Libraries :: Application Frameworks
Requires-Python: >=3.7
